taxi_petzi/__init__.py
taxi_petzi/backend.py
taxi_petzi-1.1.0.dist-info/entry_points.txt
taxi_petzi-1.1.0.dist-info/LICENSE
taxi_petzi-1.1.0.dist-info/WHEEL
taxi_petzi-1.1.0.dist-info/METADATA
taxi_petzi-1.1.0.dist-info/RECORD
