Metadata-Version: 2.1
Name: taxi_petzi
Version: 1.1.0
Summary: Taxi backend for Petzi
Author-email: Sylvain Fankhauser <sephi@fhtagn.top>
Requires-Python: >=3.7
Requires-Dist: google-api-python-client
Requires-Dist: google-auth-httplib2
Requires-Dist: google-auth-oauthlib
Requires-Dist: taxi>=6.1.0
Project-URL: Source, https://github.com/sephii/taxi-petzi
